featurizer/__init__.py
featurizer/bert_featurizer.py
rasa_chinese_plugin-0.6.0.dist-info/LICENSE
rasa_chinese_plugin-0.6.0.dist-info/METADATA
rasa_chinese_plugin-0.6.0.dist-info/WHEEL
rasa_chinese_plugin-0.6.0.dist-info/top_level.txt
rasa_chinese_plugin-0.6.0.dist-info/RECORD
