Metadata-Version: 2.1
Name: rasa-chinese-plugin
Version: 0.6.0
Summary: Rasa NLU addons a natural language parser for bots
Home-page: https://rasa.com
Author: Zhong Lei
Author-email: 625015751@qq.com
Maintainer: Zhong Lei
Maintainer-email: 625015751@qq.com
License: UNKNOWN
Download-URL: https://github.com/zlxwl/rasa_chinese_extend_plugin/archive/v0.6.0.tar.gz
Project-URL: Bug Reports, https://github.com/zlxwl/rasa_chinese_extend_plugin/issues
Project-URL: Source, https://github.com/zlxwl/rasa_chinese_extend_plugin
Keywords: nlp machine-learning machine-learning-library bot bots botkit rasa conversational-agents conversational-ai chatbotchatbot-framework bot-framework
Platform: UNKNOWN
Classifier: Programming Language :: Python :: 3
Classifier: License :: OSI Approved :: GNU Lesser General Public License v3 or later (LGPLv3+)
Classifier: Operating System :: OS Independent
Requires-Dist: rasa-nlu (==0.15.0)
Requires-Dist: rasa-core (==0.14.0)
Requires-Dist: jieba (~=0.39)
Requires-Dist: bert-serving-client (==1.8.9)
